{
  "contacts": [
    {
      "id": 1646818771650,
      "nom": "Paquentin",
      "prenom": "Clément",
      "address": "France",
      "email": "clement.fr",
      "tel": "0660107403",
      "category": "Ami"
    },
    {
      "id": 1646819064406,
      "nom": "Hayat",
      "prenom": "Alexis",
      "address": "Paris",
      "email": "alexis.fr",
      "tel": "0665259288",
      "category": "Famille",
      "isModify": 1646838075254
    },
    {
      "id": 1646821334370,
      "nom": "Garcia",
      "prenom": "Josselin",
      "address": "joselin.fr",
      "email": "garcia.fr",
      "tel": "0678598452",
      "category": "Autres",
      "isModify": 1646897530847
    },
    {
      "id": 1646823396946,
      "nom": "Papy",
      "prenom": "config",
      "address": "",
      "email": "papyconfig@hotmail.fr",
      "tel": "",
      "category": "Ami",
      "isModify": 1646840657829
    },
    {
      "id": 1646830800203,
      "nom": "esgle",
      "prenom": "Quentin",
      "address": "",
      "email": "pourpre.o@hotmail.fr",
      "tel": "",
      "category": "Ami"
    },
    {
      "nom": "Lasalle",
      "prenom": "Jean",
      "address": "campagne",
      "email": "jean.fr",
      "tel": "",
      "category": "travail",
      "isModify": 1646917116750,
      "id": 1646833237197
    },
    {
      "nom": "Sanchez",
      "prenom": "laurent",
      "address": "585 rue oui",
      "email": "alexis@hot.fr",
      "tel": "",
      "category": "travail",
      "isModify": 1646916660327,
      "id": 1646834407991
    },
    {
      "nom": "Pedro",
      "prenom": "Pascal",
      "address": "mandalore",
      "email": "mando@BY.fr",
      "tel": "911",
      "category": "Travail",
      "id": 1646834482544
    },
    {
      "nom": "Colonate",
      "prenom": "pierre",
      "address": "france",
      "email": "pierre.fr",
      "tel": "45855",
      "category": "famille",
      "isModify": 1646916902643,
      "id": 1646840581226
    },
    {
      "nom": "Ortance",
      "prenom": "depres",
      "address": "",
      "email": "drpes.fr",
      "tel": "",
      "category": "famille",
      "isModify": 1646917097477,
      "id": 1646897562738
    }
  ]
}